README.md
setup.py
ninpy/__init__.py
ninpy/common.py
ninpy/crypto.py
ninpy/data.py
ninpy/debug.py
ninpy/experiment.py
ninpy/hw.py
ninpy/hyper.py
ninpy/int8.py
ninpy/job.py
ninpy/layer_converter.py
ninpy/log.py
ninpy/losses.py
ninpy/metrics.py
ninpy/notify.py
ninpy/quant.py
ninpy/resize.py
ninpy/torch_utils.py
ninpy/yaml2.py
ninpy.egg-info/PKG-INFO
ninpy.egg-info/SOURCES.txt
ninpy.egg-info/dependency_links.txt
ninpy.egg-info/top_level.txt
ninpy/datasets/__init__.py
ninpy/datasets/camvid.py
ninpy/datasets/cinic10.py
ninpy/datasets/datasets.py
ninpy/datasets/imagenet.py
ninpy/datasets/kitti_road.py
ninpy/datasets/toy_datasets.py
ninpy/datasets/voc2012.py
ninpy/models/__init__.py
ninpy/models/cifar_resnet.py
ninpy/models/cifar_vgg.py
ninpy/models/small_models.py
ninpy/torch2/__init__.py
ninpy/torch2/module.py
ninpy/torch2/torch2.py