Metadata-Version: 1.0
Name: ninpy
Version: 0.0.1
Summary: Template files for Ninnart Fuengfusin.
Home-page: UNKNOWN
Author: Ninnart Fuengfusin
Author-email: ninnart.fuengfusin@yahoo.com
License: MIT
Platform: UNKNOWN
